{
  "pageTitle": "Donate • 0xElectron + 0xLEANux",
  "hubCanonical": "https://0xElectron.github.io/donate/",
  "recipients": {
    "dev": {
      "id": "dev",
      "label": "@0xElectron",
      "kind": "Developer",
      "profile": "https://github.com/0xElectron",
      "sponsors": "https://github.com/sponsors/0xElectron",
      "card": "YOUR_STRIPE_PAYMENT_LINK_DEV",
      "paypal": "https://www.paypal.me/0xElectron",
      "openCollective": "",
      "koFi": "https://ko-fi.com/0xElectron",
      "buyMeACoffee": "https://www.buymeacoffee.com/0xElectron",
      "patreon": "",
      "liberapay": "",
      "polar": "",
      "thanksDev": "",
      "issueHunt": "",
      "tidelift": "",
      "communityBridge": "",
      "wise": "",
      "revolut": "",
      "bankTransfer": "",
      "crypto": {
        "btc": [
          "YOUR_BTC_ADDRESS_DEV_1",
          "YOUR_BTC_ADDRESS_DEV_2"
        ],
        "eth": [
          "YOUR_ETH_ADDRESS_DEV_1",
          "YOUR_ETH_ADDRESS_DEV_2"
        ]
      },
      "wallets": {
        "metamask": {
          "btc": [
            "YOUR_METAMASK_BTC_ADDRESS_DEV"
          ],
          "eth": [
            "YOUR_METAMASK_ETH_ADDRESS_DEV_1",
            "YOUR_METAMASK_ETH_ADDRESS_DEV_2"
          ],
          "sol": [
            "YOUR_METAMASK_SOL_ADDRESS_DEV"
          ],
          "arbitrum": [
            "YOUR_METAMASK_ARBITRUM_ADDRESS_DEV"
          ],
          "base": [
            "YOUR_METAMASK_BASE_ADDRESS_DEV"
          ],
          "linea": [
            "YOUR_METAMASK_LINEA_ADDRESS_DEV"
          ],
          "polygon": [
            "YOUR_METAMASK_POLYGON_ADDRESS_DEV"
          ],
          "op": [
            "YOUR_METAMASK_OP_ADDRESS_DEV"
          ],
          "bnb": [
            "YOUR_METAMASK_BNB_ADDRESS_DEV"
          ],
          "sei": [
            "YOUR_METAMASK_SEI_ADDRESS_DEV"
          ]
        },
        "atomicwallet": {
          "btc": [
            "YOUR_BTC_ADDRESS_DEV_1",
            "YOUR_BTC_ADDRESS_DEV_2"
          ],
          "eth": [
            "YOUR_ETH_ADDRESS_DEV_1",
            "YOUR_ETH_ADDRESS_DEV_2"
          ]
        }
      }
    },
    "org": {
      "id": "org",
      "label": "@0xLEANux",
      "kind": "Organization",
      "profile": "https://github.com/0xLEANux",
      "sponsors": "https://github.com/sponsors/0xLEANux",
      "card": "YOUR_STRIPE_PAYMENT_LINK_ORG",
      "paypal": "https://www.paypal.me/0xLEANux",
      "openCollective": "",
      "koFi": "https://ko-fi.com/0xLEANux",
      "buyMeACoffee": "https://www.buymeacoffee.com/0xLEANux",
      "patreon": "",
      "liberapay": "",
      "polar": "",
      "thanksDev": "",
      "issueHunt": "",
      "tidelift": "",
      "communityBridge": "",
      "wise": "",
      "revolut": "",
      "bankTransfer": "",
      "crypto": {
        "btc": [
          "YOUR_BTC_ADDRESS_ORG_1",
          "YOUR_BTC_ADDRESS_ORG_2"
        ],
        "eth": [
          "YOUR_ETH_ADDRESS_ORG_1",
          "YOUR_ETH_ADDRESS_ORG_2"
        ]
      },
      "wallets": {
        "metamask": {
          "btc": [
            "YOUR_METAMASK_BTC_ADDRESS_ORG"
          ],
          "eth": [
            "YOUR_METAMASK_ETH_ADDRESS_ORG_1",
            "YOUR_METAMASK_ETH_ADDRESS_ORG_2"
          ],
          "sol": [
            "YOUR_METAMASK_SOL_ADDRESS_ORG"
          ],
          "arbitrum": [
            "YOUR_METAMASK_ARBITRUM_ADDRESS_ORG"
          ],
          "base": [
            "YOUR_METAMASK_BASE_ADDRESS_ORG"
          ],
          "linea": [
            "YOUR_METAMASK_LINEA_ADDRESS_ORG"
          ],
          "polygon": [
            "YOUR_METAMASK_POLYGON_ADDRESS_ORG"
          ],
          "op": [
            "YOUR_METAMASK_OP_ADDRESS_ORG"
          ],
          "bnb": [
            "YOUR_METAMASK_BNB_ADDRESS_ORG"
          ],
          "sei": [
            "YOUR_METAMASK_SEI_ADDRESS_ORG"
          ]
        },
        "atomicwallet": {
          "btc": [
            "YOUR_BTC_ADDRESS_ORG_1",
            "YOUR_BTC_ADDRESS_ORG_2"
          ],
          "eth": [
            "YOUR_ETH_ADDRESS_ORG_1",
            "YOUR_ETH_ADDRESS_ORG_2"
          ]
        }
      }
    }
  },
  "offerings": [
    { "name": "Coffee", "price": "$5", "note": "Quick thank-you for a useful project", "actions": ["card", "paypal", "sponsors", "koFi"] },
    { "name": "Supporter", "price": "$15", "note": "Helps with maintenance, docs, packaging, CI", "actions": ["card", "paypal", "sponsors", "buyMeACoffee"] },
    { "name": "Sponsor", "price": "$50", "note": "Back roadmap features, refactors, and long-term support work.", "actions": ["sponsors", "card", "paypal"] }
  ]
}
